<annotation><folder>my-project-name</folder><filename>final_0633.png</filename><path>/my-project-name/final_0633.png</path><source><database>Unspecified</database></source><size><width>1120</width><height>560</height><depth>3</depth></size><object><name>cage</name><pose>Unspecified</pose><truncated>0</truncated><difficult>0</difficult><bndbox><xmin>918</xmin><ymin>314</ymin><xmax>960</xmax><ymax>347</ymax></bndbox></object><object><name>chain</name><pose>Unspecified</pose><truncated>0</truncated><difficult>0</difficult><bndbox><xmin>614</xmin><ymin>361</ymin><xmax>648</xmax><ymax>412</ymax></bndbox></object><object><name>ball</name><pose>Unspecified</pose><truncated>0</truncated><difficult>0</difficult><bndbox><xmin>565</xmin><ymin>221</ymin><xmax>586</xmax><ymax>239</ymax></bndbox></object><object><name>ball</name><pose>Unspecified</pose><truncated>0</truncated><difficult>0</difficult><bndbox><xmin>522</xmin><ymin>408</ymin><xmax>540</xmax><ymax>423</ymax></bndbox></object><object><name>cage</name><pose>Unspecified</pose><truncated>0</truncated><difficult>0</difficult><bndbox><xmin>675</xmin><ymin>246</ymin><xmax>714</xmax><ymax>292</ymax></bndbox></object></annotation>