<annotation><folder>my-project-name</folder><filename>final_0798.png</filename><path>/my-project-name/final_0798.png</path><source><database>Unspecified</database></source><size><width>1120</width><height>560</height><depth>3</depth></size><object><name>ball</name><pose>Unspecified</pose><truncated>0</truncated><difficult>0</difficult><bndbox><xmin>312</xmin><ymin>335</ymin><xmax>327</xmax><ymax>350</ymax></bndbox></object><object><name>chain</name><pose>Unspecified</pose><truncated>0</truncated><difficult>0</difficult><bndbox><xmin>169</xmin><ymin>335</ymin><xmax>216</xmax><ymax>382</ymax></bndbox></object><object><name>chain</name><pose>Unspecified</pose><truncated>0</truncated><difficult>0</difficult><bndbox><xmin>285</xmin><ymin>340</ymin><xmax>325</xmax><ymax>402</ymax></bndbox></object></annotation>