<annotation><folder>my-project-name</folder><filename>final_0579.png</filename><path>/my-project-name/final_0579.png</path><source><database>Unspecified</database></source><size><width>1120</width><height>560</height><depth>3</depth></size><object><name>cage</name><pose>Unspecified</pose><truncated>0</truncated><difficult>0</difficult><bndbox><xmin>410</xmin><ymin>297</ymin><xmax>448</xmax><ymax>340</ymax></bndbox></object><object><name>chain</name><pose>Unspecified</pose><truncated>0</truncated><difficult>0</difficult><bndbox><xmin>815</xmin><ymin>394</ymin><xmax>851</xmax><ymax>404</ymax></bndbox></object><object><name>chain</name><pose>Unspecified</pose><truncated>0</truncated><difficult>0</difficult><bndbox><xmin>422</xmin><ymin>57</ymin><xmax>473</xmax><ymax>92</ymax></bndbox></object></annotation>