<annotation><folder>my-project-name</folder><filename>final_0398.png</filename><path>/my-project-name/final_0398.png</path><source><database>Unspecified</database></source><size><width>1120</width><height>560</height><depth>3</depth></size><object><name>AUV</name><pose>Unspecified</pose><truncated>0</truncated><difficult>0</difficult><bndbox><xmin>430</xmin><ymin>478</ymin><xmax>456</xmax><ymax>491</ymax></bndbox></object><object><name>cage</name><pose>Unspecified</pose><truncated>0</truncated><difficult>0</difficult><bndbox><xmin>723</xmin><ymin>371</ymin><xmax>757</xmax><ymax>412</ymax></bndbox></object><object><name>ball</name><pose>Unspecified</pose><truncated>0</truncated><difficult>0</difficult><bndbox><xmin>424</xmin><ymin>170</ymin><xmax>439</xmax><ymax>185</ymax></bndbox></object><object><name>cage</name><pose>Unspecified</pose><truncated>0</truncated><difficult>0</difficult><bndbox><xmin>370</xmin><ymin>99</ymin><xmax>413</xmax><ymax>141</ymax></bndbox></object><object><name>AUV</name><pose>Unspecified</pose><truncated>0</truncated><difficult>0</difficult><bndbox><xmin>1039</xmin><ymin>329</ymin><xmax>1054</xmax><ymax>356</ymax></bndbox></object><object><name>chain</name><pose>Unspecified</pose><truncated>0</truncated><difficult>0</difficult><bndbox><xmin>614</xmin><ymin>171</ymin><xmax>627</xmax><ymax>225</ymax></bndbox></object></annotation>