<annotation><folder>my-project-name</folder><filename>final_1826.png</filename><path>/my-project-name/final_1826.png</path><source><database>Unspecified</database></source><size><width>1120</width><height>560</height><depth>3</depth></size><object><name>frogman</name><pose>Unspecified</pose><truncated>0</truncated><difficult>0</difficult><bndbox><xmin>827</xmin><ymin>88</ymin><xmax>860</xmax><ymax>125</ymax></bndbox></object><object><name>AUV</name><pose>Unspecified</pose><truncated>0</truncated><difficult>0</difficult><bndbox><xmin>538</xmin><ymin>519</ymin><xmax>553</xmax><ymax>543</ymax></bndbox></object><object><name>chain</name><pose>Unspecified</pose><truncated>0</truncated><difficult>0</difficult><bndbox><xmin>362</xmin><ymin>451</ymin><xmax>404</xmax><ymax>464</ymax></bndbox></object><object><name>ball</name><pose>Unspecified</pose><truncated>0</truncated><difficult>0</difficult><bndbox><xmin>578</xmin><ymin>284</ymin><xmax>598</xmax><ymax>305</ymax></bndbox></object><object><name>cage</name><pose>Unspecified</pose><truncated>0</truncated><difficult>0</difficult><bndbox><xmin>716</xmin><ymin>187</ymin><xmax>749</xmax><ymax>217</ymax></bndbox></object></annotation>