<annotation><folder>my-project-name</folder><filename>final_1434.png</filename><path>/my-project-name/final_1434.png</path><source><database>Unspecified</database></source><size><width>1120</width><height>560</height><depth>3</depth></size><object><name>chain</name><pose>Unspecified</pose><truncated>0</truncated><difficult>0</difficult><bndbox><xmin>618</xmin><ymin>351</ymin><xmax>668</xmax><ymax>371</ymax></bndbox></object><object><name>frogman</name><pose>Unspecified</pose><truncated>0</truncated><difficult>0</difficult><bndbox><xmin>753</xmin><ymin>285</ymin><xmax>772</xmax><ymax>324</ymax></bndbox></object><object><name>ball</name><pose>Unspecified</pose><truncated>0</truncated><difficult>0</difficult><bndbox><xmin>633</xmin><ymin>301</ymin><xmax>654</xmax><ymax>323</ymax></bndbox></object></annotation>