<annotation><folder>my-project-name</folder><filename>final_0096.png</filename><path>/my-project-name/final_0096.png</path><source><database>Unspecified</database></source><size><width>1120</width><height>560</height><depth>3</depth></size><object><name>cage</name><pose>Unspecified</pose><truncated>0</truncated><difficult>0</difficult><bndbox><xmin>523</xmin><ymin>226</ymin><xmax>552</xmax><ymax>266</ymax></bndbox></object><object><name>AUV</name><pose>Unspecified</pose><truncated>0</truncated><difficult>0</difficult><bndbox><xmin>173</xmin><ymin>208</ymin><xmax>196</xmax><ymax>227</ymax></bndbox></object><object><name>ball</name><pose>Unspecified</pose><truncated>0</truncated><difficult>0</difficult><bndbox><xmin>167</xmin><ymin>327</ymin><xmax>185</xmax><ymax>348</ymax></bndbox></object></annotation>