<annotation><folder>my-project-name</folder><filename>final_0948.png</filename><path>/my-project-name/final_0948.png</path><source><database>Unspecified</database></source><size><width>1120</width><height>560</height><depth>3</depth></size><object><name>cage</name><pose>Unspecified</pose><truncated>0</truncated><difficult>0</difficult><bndbox><xmin>693</xmin><ymin>186</ymin><xmax>721</xmax><ymax>206</ymax></bndbox></object><object><name>ball</name><pose>Unspecified</pose><truncated>0</truncated><difficult>0</difficult><bndbox><xmin>541</xmin><ymin>107</ymin><xmax>560</xmax><ymax>128</ymax></bndbox></object><object><name>chain</name><pose>Unspecified</pose><truncated>0</truncated><difficult>0</difficult><bndbox><xmin>659</xmin><ymin>251</ymin><xmax>676</xmax><ymax>303</ymax></bndbox></object><object><name>frogman</name><pose>Unspecified</pose><truncated>0</truncated><difficult>0</difficult><bndbox><xmin>528</xmin><ymin>156</ymin><xmax>553</xmax><ymax>182</ymax></bndbox></object><object><name>chain</name><pose>Unspecified</pose><truncated>0</truncated><difficult>0</difficult><bndbox><xmin>566</xmin><ymin>149</ymin><xmax>593</xmax><ymax>194</ymax></bndbox></object></annotation>