<annotation><folder>my-project-name</folder><filename>final_1153.png</filename><path>/my-project-name/final_1153.png</path><source><database>Unspecified</database></source><size><width>1120</width><height>560</height><depth>3</depth></size><object><name>cage</name><pose>Unspecified</pose><truncated>0</truncated><difficult>0</difficult><bndbox><xmin>605</xmin><ymin>203</ymin><xmax>668</xmax><ymax>249</ymax></bndbox></object><object><name>cage</name><pose>Unspecified</pose><truncated>0</truncated><difficult>0</difficult><bndbox><xmin>768</xmin><ymin>273</ymin><xmax>826</xmax><ymax>340</ymax></bndbox></object><object><name>AUV</name><pose>Unspecified</pose><truncated>0</truncated><difficult>0</difficult><bndbox><xmin>360</xmin><ymin>155</ymin><xmax>398</xmax><ymax>194</ymax></bndbox></object><object><name>frogman</name><pose>Unspecified</pose><truncated>0</truncated><difficult>0</difficult><bndbox><xmin>682</xmin><ymin>312</ymin><xmax>729</xmax><ymax>372</ymax></bndbox></object></annotation>