<annotation><folder>chibi</folder><filename>chibi_enhanced_0283.png</filename><path>complete_enhanced/chibi/final_images/chibi_enhanced_0283.png</path><size><width>1120</width><height>560</height><depth>3</depth></size><object><name>cage</name><pose>Unspecified</pose><truncated>0</truncated><difficult>0</difficult><bndbox><xmin>548</xmin><ymin>134</ymin><xmax>611</xmax><ymax>218</ymax></bndbox></object><object><name>frogman</name><pose>Unspecified</pose><truncated>0</truncated><difficult>0</difficult><bndbox><xmin>543</xmin><ymin>333</ymin><xmax>611</xmax><ymax>380</ymax></bndbox></object><object><name>ball</name><pose>Unspecified</pose><truncated>0</truncated><difficult>0</difficult><bndbox><xmin>554</xmin><ymin>425</ymin><xmax>614</xmax><ymax>466</ymax></bndbox></object></annotation>