<annotation><folder>my-project-name</folder><filename>final_1790.png</filename><path>/my-project-name/final_1790.png</path><source><database>Unspecified</database></source><size><width>1120</width><height>560</height><depth>3</depth></size><object><name>cage</name><pose>Unspecified</pose><truncated>0</truncated><difficult>0</difficult><bndbox><xmin>414</xmin><ymin>367</ymin><xmax>497</xmax><ymax>442</ymax></bndbox></object><object><name>AUV</name><pose>Unspecified</pose><truncated>0</truncated><difficult>0</difficult><bndbox><xmin>530</xmin><ymin>94</ymin><xmax>561</xmax><ymax>120</ymax></bndbox></object><object><name>chain</name><pose>Unspecified</pose><truncated>0</truncated><difficult>0</difficult><bndbox><xmin>813</xmin><ymin>293</ymin><xmax>847</xmax><ymax>374</ymax></bndbox></object></annotation>