<annotation><folder>my-project-name</folder><filename>final_1803.png</filename><path>/my-project-name/final_1803.png</path><source><database>Unspecified</database></source><size><width>1120</width><height>560</height><depth>3</depth></size><object><name>AUV</name><pose>Unspecified</pose><truncated>0</truncated><difficult>0</difficult><bndbox><xmin>867</xmin><ymin>227</ymin><xmax>896</xmax><ymax>275</ymax></bndbox></object><object><name>chain</name><pose>Unspecified</pose><truncated>0</truncated><difficult>0</difficult><bndbox><xmin>207</xmin><ymin>233</ymin><xmax>229</xmax><ymax>304</ymax></bndbox></object><object><name>ball</name><pose>Unspecified</pose><truncated>0</truncated><difficult>0</difficult><bndbox><xmin>134</xmin><ymin>319</ymin><xmax>169</xmax><ymax>356</ymax></bndbox></object><object><name>ball</name><pose>Unspecified</pose><truncated>0</truncated><difficult>0</difficult><bndbox><xmin>420</xmin><ymin>409</ymin><xmax>458</xmax><ymax>446</ymax></bndbox></object><object><name>frogman</name><pose>Unspecified</pose><truncated>0</truncated><difficult>0</difficult><bndbox><xmin>822</xmin><ymin>203</ymin><xmax>857</xmax><ymax>282</ymax></bndbox></object><object><name>ball</name><pose>Unspecified</pose><truncated>0</truncated><difficult>0</difficult><bndbox><xmin>784</xmin><ymin>294</ymin><xmax>817</xmax><ymax>331</ymax></bndbox></object></annotation>