<annotation><folder>my-project-name</folder><filename>final_0462.png</filename><path>/my-project-name/final_0462.png</path><source><database>Unspecified</database></source><size><width>1120</width><height>560</height><depth>3</depth></size><object><name>AUV</name><pose>Unspecified</pose><truncated>0</truncated><difficult>0</difficult><bndbox><xmin>576</xmin><ymin>158</ymin><xmax>613</xmax><ymax>198</ymax></bndbox></object><object><name>ball</name><pose>Unspecified</pose><truncated>0</truncated><difficult>0</difficult><bndbox><xmin>607</xmin><ymin>131</ymin><xmax>641</xmax><ymax>167</ymax></bndbox></object><object><name>cage</name><pose>Unspecified</pose><truncated>0</truncated><difficult>0</difficult><bndbox><xmin>476</xmin><ymin>241</ymin><xmax>568</xmax><ymax>337</ymax></bndbox></object></annotation>