<annotation><folder>my-project-name</folder><filename>final_0608.png</filename><path>/my-project-name/final_0608.png</path><source><database>Unspecified</database></source><size><width>1120</width><height>560</height><depth>3</depth></size><object><name>cage</name><pose>Unspecified</pose><truncated>0</truncated><difficult>0</difficult><bndbox><xmin>433</xmin><ymin>104</ymin><xmax>506</xmax><ymax>190</ymax></bndbox></object><object><name>chain</name><pose>Unspecified</pose><truncated>0</truncated><difficult>0</difficult><bndbox><xmin>863</xmin><ymin>260</ymin><xmax>902</xmax><ymax>356</ymax></bndbox></object><object><name>cage</name><pose>Unspecified</pose><truncated>0</truncated><difficult>0</difficult><bndbox><xmin>694</xmin><ymin>111</ymin><xmax>738</xmax><ymax>167</ymax></bndbox></object><object><name>ball</name><pose>Unspecified</pose><truncated>0</truncated><difficult>0</difficult><bndbox><xmin>620</xmin><ymin>452</ymin><xmax>655</xmax><ymax>490</ymax></bndbox></object></annotation>