<annotation><folder>my-project-name</folder><filename>final_0909.png</filename><path>/my-project-name/final_0909.png</path><source><database>Unspecified</database></source><size><width>1120</width><height>560</height><depth>3</depth></size><object><name>AUV</name><pose>Unspecified</pose><truncated>0</truncated><difficult>0</difficult><bndbox><xmin>529</xmin><ymin>178</ymin><xmax>576</xmax><ymax>215</ymax></bndbox></object><object><name>frogman</name><pose>Unspecified</pose><truncated>0</truncated><difficult>0</difficult><bndbox><xmin>314</xmin><ymin>186</ymin><xmax>391</xmax><ymax>234</ymax></bndbox></object><object><name>ball</name><pose>Unspecified</pose><truncated>0</truncated><difficult>0</difficult><bndbox><xmin>501</xmin><ymin>274</ymin><xmax>531</xmax><ymax>307</ymax></bndbox></object></annotation>