<annotation><folder>my-project-name</folder><filename>final_2233.png</filename><path>/my-project-name/final_2233.png</path><source><database>Unspecified</database></source><size><width>1120</width><height>560</height><depth>3</depth></size><object><name>chain</name><pose>Unspecified</pose><truncated>0</truncated><difficult>0</difficult><bndbox><xmin>268</xmin><ymin>123</ymin><xmax>283</xmax><ymax>144</ymax></bndbox></object><object><name>frogman</name><pose>Unspecified</pose><truncated>0</truncated><difficult>0</difficult><bndbox><xmin>617</xmin><ymin>236</ymin><xmax>629</xmax><ymax>256</ymax></bndbox></object><object><name>ball</name><pose>Unspecified</pose><truncated>0</truncated><difficult>0</difficult><bndbox><xmin>294</xmin><ymin>75</ymin><xmax>307</xmax><ymax>89</ymax></bndbox></object><object><name>ball</name><pose>Unspecified</pose><truncated>0</truncated><difficult>0</difficult><bndbox><xmin>298</xmin><ymin>163</ymin><xmax>311</xmax><ymax>176</ymax></bndbox></object></annotation>