<annotation><folder>my-project-name</folder><filename>final_1880.png</filename><path>/my-project-name/final_1880.png</path><source><database>Unspecified</database></source><size><width>1120</width><height>560</height><depth>3</depth></size><object><name>chain</name><pose>Unspecified</pose><truncated>0</truncated><difficult>0</difficult><bndbox><xmin>523</xmin><ymin>188</ymin><xmax>539</xmax><ymax>208</ymax></bndbox></object><object><name>frogman</name><pose>Unspecified</pose><truncated>0</truncated><difficult>0</difficult><bndbox><xmin>718</xmin><ymin>304</ymin><xmax>733</xmax><ymax>325</ymax></bndbox></object><object><name>ball</name><pose>Unspecified</pose><truncated>0</truncated><difficult>0</difficult><bndbox><xmin>256</xmin><ymin>377</ymin><xmax>268</xmax><ymax>389</ymax></bndbox></object><object><name>chain</name><pose>Unspecified</pose><truncated>0</truncated><difficult>0</difficult><bndbox><xmin>735</xmin><ymin>227</ymin><xmax>768</xmax><ymax>245</ymax></bndbox></object><object><name>chain</name><pose>Unspecified</pose><truncated>0</truncated><difficult>0</difficult><bndbox><xmin>518</xmin><ymin>360</ymin><xmax>525</xmax><ymax>390</ymax></bndbox></object><object><name>chain</name><pose>Unspecified</pose><truncated>0</truncated><difficult>0</difficult><bndbox><xmin>452</xmin><ymin>195</ymin><xmax>458</xmax><ymax>218</ymax></bndbox></object></annotation>