<annotation><folder>my-project-name</folder><filename>final_0043.png</filename><path>/my-project-name/final_0043.png</path><source><database>Unspecified</database></source><size><width>1120</width><height>560</height><depth>3</depth></size><object><name>frogman</name><pose>Unspecified</pose><truncated>0</truncated><difficult>0</difficult><bndbox><xmin>650</xmin><ymin>239</ymin><xmax>663</xmax><ymax>261</ymax></bndbox></object><object><name>cage</name><pose>Unspecified</pose><truncated>0</truncated><difficult>0</difficult><bndbox><xmin>1048</xmin><ymin>326</ymin><xmax>1072</xmax><ymax>350</ymax></bndbox></object><object><name>chain</name><pose>Unspecified</pose><truncated>0</truncated><difficult>0</difficult><bndbox><xmin>657</xmin><ymin>405</ymin><xmax>687</xmax><ymax>425</ymax></bndbox></object><object><name>frogman</name><pose>Unspecified</pose><truncated>0</truncated><difficult>0</difficult><bndbox><xmin>902</xmin><ymin>331</ymin><xmax>920</xmax><ymax>350</ymax></bndbox></object></annotation>