<annotation><folder>my-project-name</folder><filename>final_2686.png</filename><path>/my-project-name/final_2686.png</path><source><database>Unspecified</database></source><size><width>1120</width><height>560</height><depth>3</depth></size><object><name>AUV</name><pose>Unspecified</pose><truncated>0</truncated><difficult>0</difficult><bndbox><xmin>464</xmin><ymin>184</ymin><xmax>479</xmax><ymax>196</ymax></bndbox></object><object><name>AUV</name><pose>Unspecified</pose><truncated>0</truncated><difficult>0</difficult><bndbox><xmin>294</xmin><ymin>288</ymin><xmax>309</xmax><ymax>304</ymax></bndbox></object><object><name>ball</name><pose>Unspecified</pose><truncated>0</truncated><difficult>0</difficult><bndbox><xmin>378</xmin><ymin>468</ymin><xmax>391</xmax><ymax>481</ymax></bndbox></object></annotation>