<annotation><folder>my-project-name</folder><filename>final_0570.png</filename><path>/my-project-name/final_0570.png</path><source><database>Unspecified</database></source><size><width>1120</width><height>560</height><depth>3</depth></size><object><name>frogman</name><pose>Unspecified</pose><truncated>0</truncated><difficult>0</difficult><bndbox><xmin>694</xmin><ymin>145</ymin><xmax>717</xmax><ymax>157</ymax></bndbox></object><object><name>cage</name><pose>Unspecified</pose><truncated>0</truncated><difficult>0</difficult><bndbox><xmin>550</xmin><ymin>264</ymin><xmax>575</xmax><ymax>282</ymax></bndbox></object><object><name>cage</name><pose>Unspecified</pose><truncated>0</truncated><difficult>0</difficult><bndbox><xmin>878</xmin><ymin>377</ymin><xmax>909</xmax><ymax>399</ymax></bndbox></object><object><name>chain</name><pose>Unspecified</pose><truncated>0</truncated><difficult>0</difficult><bndbox><xmin>371</xmin><ymin>83</ymin><xmax>395</xmax><ymax>109</ymax></bndbox></object><object><name>frogman</name><pose>Unspecified</pose><truncated>0</truncated><difficult>0</difficult><bndbox><xmin>647</xmin><ymin>323</ymin><xmax>660</xmax><ymax>343</ymax></bndbox></object></annotation>