<annotation><folder>my-project-name</folder><filename>final_2964.png</filename><path>/my-project-name/final_2964.png</path><source><database>Unspecified</database></source><size><width>1120</width><height>560</height><depth>3</depth></size><object><name>cage</name><pose>Unspecified</pose><truncated>0</truncated><difficult>0</difficult><bndbox><xmin>466</xmin><ymin>59</ymin><xmax>497</xmax><ymax>89</ymax></bndbox></object><object><name>chain</name><pose>Unspecified</pose><truncated>0</truncated><difficult>0</difficult><bndbox><xmin>727</xmin><ymin>266</ymin><xmax>736</xmax><ymax>296</ymax></bndbox></object><object><name>ball</name><pose>Unspecified</pose><truncated>0</truncated><difficult>0</difficult><bndbox><xmin>691</xmin><ymin>480</ymin><xmax>706</xmax><ymax>494</ymax></bndbox></object></annotation>