<annotation><folder>my-project-name</folder><filename>final_1873.png</filename><path>/my-project-name/final_1873.png</path><source><database>Unspecified</database></source><size><width>1120</width><height>560</height><depth>3</depth></size><object><name>cage</name><pose>Unspecified</pose><truncated>0</truncated><difficult>0</difficult><bndbox><xmin>296</xmin><ymin>350</ymin><xmax>322</xmax><ymax>375</ymax></bndbox></object><object><name>ball</name><pose>Unspecified</pose><truncated>0</truncated><difficult>0</difficult><bndbox><xmin>386</xmin><ymin>257</ymin><xmax>400</xmax><ymax>270</ymax></bndbox></object><object><name>chain</name><pose>Unspecified</pose><truncated>0</truncated><difficult>0</difficult><bndbox><xmin>541</xmin><ymin>101</ymin><xmax>548</xmax><ymax>130</ymax></bndbox></object><object><name>cage</name><pose>Unspecified</pose><truncated>0</truncated><difficult>0</difficult><bndbox><xmin>943</xmin><ymin>194</ymin><xmax>967</xmax><ymax>212</ymax></bndbox></object><object><name>chain</name><pose>Unspecified</pose><truncated>0</truncated><difficult>0</difficult><bndbox><xmin>831</xmin><ymin>370</ymin><xmax>853</xmax><ymax>399</ymax></bndbox></object></annotation>