<annotation><folder>my-project-name</folder><filename>final_0458.png</filename><path>/my-project-name/final_0458.png</path><source><database>Unspecified</database></source><size><width>1120</width><height>560</height><depth>3</depth></size><object><name>chain</name><pose>Unspecified</pose><truncated>0</truncated><difficult>0</difficult><bndbox><xmin>413</xmin><ymin>178</ymin><xmax>430</xmax><ymax>213</ymax></bndbox></object><object><name>chain</name><pose>Unspecified</pose><truncated>0</truncated><difficult>0</difficult><bndbox><xmin>155</xmin><ymin>347</ymin><xmax>185</xmax><ymax>368</ymax></bndbox></object><object><name>frogman</name><pose>Unspecified</pose><truncated>0</truncated><difficult>0</difficult><bndbox><xmin>482</xmin><ymin>9</ymin><xmax>499</xmax><ymax>18</ymax></bndbox></object><object><name>chain</name><pose>Unspecified</pose><truncated>0</truncated><difficult>0</difficult><bndbox><xmin>113</xmin><ymin>304</ymin><xmax>135</xmax><ymax>332</ymax></bndbox></object><object><name>ball</name><pose>Unspecified</pose><truncated>0</truncated><difficult>0</difficult><bndbox><xmin>891</xmin><ymin>173</ymin><xmax>904</xmax><ymax>187</ymax></bndbox></object><object><name>frogman</name><pose>Unspecified</pose><truncated>0</truncated><difficult>0</difficult><bndbox><xmin>954</xmin><ymin>243</ymin><xmax>975</xmax><ymax>266</ymax></bndbox></object></annotation>