<annotation><folder>my-project-name</folder><filename>final_0697.png</filename><path>/my-project-name/final_0697.png</path><source><database>Unspecified</database></source><size><width>1120</width><height>560</height><depth>3</depth></size><object><name>AUV</name><pose>Unspecified</pose><truncated>0</truncated><difficult>0</difficult><bndbox><xmin>753</xmin><ymin>204</ymin><xmax>768</xmax><ymax>214</ymax></bndbox></object><object><name>cage</name><pose>Unspecified</pose><truncated>0</truncated><difficult>0</difficult><bndbox><xmin>733</xmin><ymin>267</ymin><xmax>759</xmax><ymax>290</ymax></bndbox></object><object><name>chain</name><pose>Unspecified</pose><truncated>0</truncated><difficult>0</difficult><bndbox><xmin>179</xmin><ymin>266</ymin><xmax>209</xmax><ymax>286</ymax></bndbox></object><object><name>cage</name><pose>Unspecified</pose><truncated>0</truncated><difficult>0</difficult><bndbox><xmin>352</xmin><ymin>362</ymin><xmax>378</xmax><ymax>391</ymax></bndbox></object></annotation>