<annotation><folder>my-project-name</folder><filename>final_0874.png</filename><path>/my-project-name/final_0874.png</path><source><database>Unspecified</database></source><size><width>1120</width><height>560</height><depth>3</depth></size><object><name>cage</name><pose>Unspecified</pose><truncated>0</truncated><difficult>0</difficult><bndbox><xmin>963</xmin><ymin>361</ymin><xmax>987</xmax><ymax>383</ymax></bndbox></object><object><name>AUV</name><pose>Unspecified</pose><truncated>0</truncated><difficult>0</difficult><bndbox><xmin>285</xmin><ymin>390</ymin><xmax>302</xmax><ymax>402</ymax></bndbox></object><object><name>chain</name><pose>Unspecified</pose><truncated>0</truncated><difficult>0</difficult><bndbox><xmin>774</xmin><ymin>363</ymin><xmax>785</xmax><ymax>389</ymax></bndbox></object><object><name>cage</name><pose>Unspecified</pose><truncated>0</truncated><difficult>0</difficult><bndbox><xmin>296</xmin><ymin>302</ymin><xmax>321</xmax><ymax>321</ymax></bndbox></object><object><name>AUV</name><pose>Unspecified</pose><truncated>0</truncated><difficult>0</difficult><bndbox><xmin>844</xmin><ymin>138</ymin><xmax>855</xmax><ymax>154</ymax></bndbox></object><object><name>frogman</name><pose>Unspecified</pose><truncated>0</truncated><difficult>0</difficult><bndbox><xmin>848</xmin><ymin>165</ymin><xmax>871</xmax><ymax>182</ymax></bndbox></object></annotation>